spring_kernel/__init__.py
spring_kernel/__main__.py
spring_kernel/install.py
spring_kernel/kernel-config.json
spring_kernel/kernel.py
spring_kernel/spring_connector.py
spring_kernel/utils.py
spring_kernel/resources/logo-32x32.png
spring_kernel/resources/logo-64x64.png
spring_kernel-1.0.3.dist-info/DESCRIPTION.rst
spring_kernel-1.0.3.dist-info/METADATA
spring_kernel-1.0.3.dist-info/RECORD
spring_kernel-1.0.3.dist-info/WHEEL
spring_kernel-1.0.3.dist-info/entry_points.txt
spring_kernel-1.0.3.dist-info/metadata.json
spring_kernel-1.0.3.dist-info/top_level.txt
