Metadata-Version: 2.0
Name: spring-kernel
Version: 1.0.3
Summary: Jupyter kernel for SpringRTS
Home-page: https://github.com/gajop/spring-kernel
Author: gajop
Author-email: gajopetrovic@gmail.com
License: MIT
Keywords: springrts jupyter ipython
Platform: UNKNOWN
Classifier: Development Status :: 3 - Alpha
Classifier: Intended Audience :: Developers
Classifier: License :: OSI Approved :: MIT License
Classifier: Framework :: IPython
Classifier: Development Status :: 4 - Beta
Classifier: Programming Language :: Python :: 2
Classifier: Programming Language :: Python :: 2.7
Classifier: Programming Language :: Python :: 3
Classifier: Programming Language :: Python :: 3.3
Classifier: Programming Language :: Python :: 3.4
Classifier: Programming Language :: Python :: 3.5
Requires-Dist: setuptools
Requires-Dist: ipykernel (>=4.0)
Requires-Dist: jupyter-client (>=4.0)
Requires-Dist: jupyter
